CHANGES.txt
IGNORE.txt
README.txt
setup.cfg
setup.py
collective/__init__.py
collective.portlet.keywordmatches.egg-info/PKG-INFO
collective.portlet.keywordmatches.egg-info/SOURCES.txt
collective.portlet.keywordmatches.egg-info/dependency_links.txt
collective.portlet.keywordmatches.egg-info/entry_points.txt
collective.portlet.keywordmatches.egg-info/namespace_packages.txt
collective.portlet.keywordmatches.egg-info/not-zip-safe
collective.portlet.keywordmatches.egg-info/requires.txt
collective.portlet.keywordmatches.egg-info/top_level.txt
collective/portlet/__init__.py
collective/portlet/keywordmatches/__init__.py
collective/portlet/keywordmatches/configure.zcml
collective/portlet/keywordmatches/keywordmatches.pt
collective/portlet/keywordmatches/keywordmatches.py
collective/portlet/keywordmatches/usei18ndude.sh
collective/portlet/keywordmatches/version.txt
collective/portlet/keywordmatches/locales/collective.portlet.keywordmatches.pot
collective/portlet/keywordmatches/locales/cs/LC_MESSAGES/collective.portlet.keywordmatches.mo
collective/portlet/keywordmatches/locales/cs/LC_MESSAGES/collective.portlet.keywordmatches.po
collective/portlet/keywordmatches/profiles/default/metadata.xml
collective/portlet/keywordmatches/profiles/default/portlets.xml
collective/portlet/keywordmatches/tests/__init__.py
collective/portlet/keywordmatches/tests/base.py
collective/portlet/keywordmatches/tests/test_portlet.py
docs/INSTALL.txt
docs/LICENSE.GPL
docs/LICENSE.txt