Metadata-Version: 1.0
Name: collective.portlet.keywordmatches
Version: 1.1
Summary: A Plone portlet to display items with similar keywords
Home-page: http://www.sixfeetup.com
Author: Lucie Lejard
Author-email: lucie@sixfeetup.com
License: GPL
Platform: UNKNOWN
Classifier: Framework :: Plone
Classifier: Framework :: Zope2
Classifier: Framework :: Zope3
Classifier: Programming Language :: Python
Classifier: Topic :: Software Development :: Libraries :: Python Modules
